{
	"configurations" : 
	[
		{
			"directories" : 
			[
				{
					"build" : ".",
					"hasInstallRule" : true,
					"jsonFile" : "directory-.-f481940814a41b180e42.json",
					"minimumCMakeVersion" : 
					{
						"string" : "3.12"
					},
					"projectIndex" : 0,
					"source" : ".",
					"targetIndexes" : 
					[
						0,
						1,
						2,
						3
					]
				}
			],
			"name" : "",
			"projects" : 
			[
				{
					"directoryIndexes" : 
					[
						0
					],
					"name" : "aura_navigation",
					"targetIndexes" : 
					[
						0,
						1,
						2,
						3
					]
				}
			],
			"targets" : 
			[
				{
					"directoryIndex" : 0,
					"id" : "ament_cmake_python_build_aura_navigation_egg::@6890427a1f51a3e7e1df",
					"jsonFile" : "target-ament_cmake_python_build_aura_navigation_egg-7fdfaac4403f4487ecdc.json",
					"name" : "ament_cmake_python_build_aura_navigation_egg",
					"projectIndex" : 0
				},
				{
					"directoryIndex" : 0,
					"id" : "ament_cmake_python_copy_aura_navigation::@6890427a1f51a3e7e1df",
					"jsonFile" : "target-ament_cmake_python_copy_aura_navigation-cea22627776b64265eac.json",
					"name" : "ament_cmake_python_copy_aura_navigation",
					"projectIndex" : 0
				},
				{
					"directoryIndex" : 0,
					"id" : "aura_navigation_uninstall::@6890427a1f51a3e7e1df",
					"jsonFile" : "target-aura_navigation_uninstall-9e454567c80561e424b9.json",
					"name" : "aura_navigation_uninstall",
					"projectIndex" : 0
				},
				{
					"directoryIndex" : 0,
					"id" : "uninstall::@6890427a1f51a3e7e1df",
					"jsonFile" : "target-uninstall-2558ed1ef936da80a2d7.json",
					"name" : "uninstall",
					"projectIndex" : 0
				}
			]
		}
	],
	"kind" : "codemodel",
	"paths" : 
	{
		"build" : "/home/utk/aura_ws/build/aura_navigation",
		"source" : "/home/utk/aura_ws/src/aura_navigation"
	},
	"version" : 
	{
		"major" : 2,
		"minor" : 3
	}
}
